tpd_pete/__init__.py
tpd_pete/__main__.py
tpd_pete/actionmanager.py
tpd_pete/enums.py
tpd_pete/ihook.py
tpd_pete/pete.py
tpd_pete/validator.py
tpd_pete/actions/__init__.py
tpd_pete/actions/configure.py
tpd_pete/actions/create_project.py
tpd_pete/actions/deploymentaction.py
tpd_pete/actions/iaction.py
tpd_pete/actions/localoverride.py
tpd_pete/actions/deployment/__init__.py
tpd_pete/actions/deployment/amplifydeployment.py
tpd_pete/actions/deployment/cloudformationdeployment.py
tpd_pete/actions/deployment/hookdeployment.py
tpd_pete/actions/deployment/ideploymentaction.py
tpd_pete/actions/deployment/zappadeployment.py
tpd_pete/template/__init__.py
tpd_pete/template/template.py
tpd_pete/tools/__init__.py
tpd_pete/tools/awscli.py
tpd_pete/tools/boto.py
tpd_pete/tools/configuration.py
tpd_pete/tools/hooksmanager.py
tpd_pete/tools/template.py
tpd_pete-0.7.1.dist-info/LICENSE.txt
tpd_pete-0.7.1.dist-info/METADATA
tpd_pete-0.7.1.dist-info/WHEEL
tpd_pete-0.7.1.dist-info/entry_points.txt
tpd_pete-0.7.1.dist-info/top_level.txt
tpd_pete-0.7.1.dist-info/RECORD
