Metadata-Version: 2.1
Name: tpd-pete
Version: 0.7.1
Summary: TPD Pete is a AWS Deployment tool for AWS Cloudformation
Home-page: https://github.com/totalpunch/TPD-Pete
Download-URL: https://github.com/totalpunch/TPD-Pete/archive/0.7.1.tar.gz
Author: TotalPunch Development
Author-email: info@totalpunch.nl
License: MIT
Requires-Python: >=3.9
License-File: LICENSE.txt
Requires-Dist: boto3 (>=1.26.22)
Requires-Dist: pyinquirer (==1.0.3)
Requires-Dist: termcolor (==2.0.1)
Requires-Dist: cfn-flip (>=1.3.0)
